{
  "version": "7",
  "dialect": "postgresql",
  "entries": [
    {
      "idx": 0,
      "version": "7",
      "when": 1722482375924,
      "tag": "0000_majestic_quasimodo",
      "breakpoints": true
    },
    {
      "idx": 1,
      "version": "7",
      "when": 1722483226671,
      "tag": "0001_eager_hercules",
      "breakpoints": true
    },
    {
      "idx": 2,
      "version": "7",
      "when": 1722702279762,
      "tag": "0002_aspiring_raza",
      "breakpoints": true
    },
    {
      "idx": 3,
      "version": "7",
      "when": 1722702687472,
      "tag": "0003_lame_mathemanic",
      "breakpoints": true
    },
    {
      "idx": 4,
      "version": "7",
      "when": 1723089190207,
      "tag": "0004_white_greymalkin",
      "breakpoints": true
    },
    {
      "idx": 5,
      "version": "7",
      "when": 1724298005178,
      "tag": "0005_massive_ma_gnuci",
      "breakpoints": true
    }
  ]
}